gui_package_cawilvitro.py
gui_package_cawilvitro-0.0.9.dist-info/METADATA
gui_package_cawilvitro-0.0.9.dist-info/WHEEL
gui_package_cawilvitro-0.0.9.dist-info/licenses/LICENSE
gui_package_cawilvitro-0.0.9.dist-info/RECORD
